envmap/__init__.py
envmap/environmentmap.py
envmap/projections.py
envmap/rotations.py
envmap/test_environmentmap.py
envmap/tetrahedronSolidAngle.py
envmap/xmlhelper.py
ezexr/__init__.py
hdrio/__init__.py
hdrtools/__init__.py
hdrtools/gsolve.py
hdrtools/sunutils.py
hdrtools/tonemapping/__init__.py
skydb/__init__.py
tools3d/__init__.py
tools3d/display.py
tools3d/spharm.py
skylibs-0.6.6.dist-info/LICENSE
skylibs-0.6.6.dist-info/METADATA
skylibs-0.6.6.dist-info/WHEEL
skylibs-0.6.6.dist-info/top_level.txt
skylibs-0.6.6.dist-info/RECORD
