Metadata-Version: 2.1
Name: skylibs
Version: 0.6.6
Summary: Tools to read, write, perform projections and handle LDR/HDR environment maps (IBL).
Home-page: https://github.com/soravux/skylibs
Author: Yannick Hold
Author-email: yannickhold@gmail.com
License: LGPLv3
Platform: UNKNOWN
License-File: LICENSE
Requires-Dist: imageio (>=1.6)
Requires-Dist: tqdm
Requires-Dist: numpy
Requires-Dist: scipy
